corelogic/__init__.py
corelogic/amortizacion.py
corelogic/analisis_ratio.py
corelogic/depreciacion.py
corelogic/excepciones.py
corelogic/interes_compuesto.py
corelogic/vpn.py
corelogic_finance-1.0.0.dist-info/licenses/LICENSE
corelogic_finance-1.0.0.dist-info/METADATA
corelogic_finance-1.0.0.dist-info/WHEEL
corelogic_finance-1.0.0.dist-info/top_level.txt
corelogic_finance-1.0.0.dist-info/RECORD
