Metadata-Version: 2.4
Name: corelogic-finance
Version: 1.0.0
Summary: Una librería robusta y precisa para cálculos financieros y de negocios, basada en principios de POO y Test-Driven Development.
Home-page: https://github.com/Aspy2005/corelogic-finance
Author: Luis Alejandro Martinez Marin
Author-email: Luis Alejandro Martinez Marin <lalejandro.2005martinez@gmail.com>
License: MIT License
Project-URL: Homepage, https://github.com/Aspy2005/corelogic-finance
Project-URL: Bug Tracker, https://github.com/Aspy2005/corelogic-finance/issues
Keywords: finance,contabilidad,vpn,amortizacion,depreciacion,tdd
Classifier: Programming Language :: Python :: 3
Classifier: License :: OSI Approved :: MIT License
Classifier: Operating System :: OS Independent
Classifier: Topic :: Office/Business :: Financial
Classifier: Topic :: Scientific/Engineering :: Mathematics
Requires-Python: >=3.11
License-File: LICENSE
Requires-Dist: numpy
Requires-Dist: numpy-financial
Requires-Dist: pandas
Dynamic: author
Dynamic: home-page
Dynamic: license-file
Dynamic: requires-python
